ctrlv.py
ctrlv_client/__init__.py
ctrlv_client/config.py
ctrlv_client/populate.json
ctrlv_client/app/__init__.py
ctrlv_client/app/helpers.py
ctrlv_client/app/main/__init__.py
ctrlv_client/app/main/forms.py
ctrlv_client/app/main/views.py
ctrlv_client/app/models/__init__.py
ctrlv_client/app/models/snippet.py
ctrlv_client/app/models/user.py
ctrlv_client/app/static/css/app.css
ctrlv_client/app/static/css/bootstrap.min.css
ctrlv_client/app/templates/base.html
ctrlv_client/app/templates/error/404.html
ctrlv_client/app/templates/error/500.html
ctrlv_client/app/templates/main/edit.html
ctrlv_client/app/templates/main/index.html
ctrlv_client/app/templates/main/login.html
ctrlv_client/app/templates/main/new.html
ctrlv_client/app/templates/main/view.html
ctrlv-0.0.1.dist-info/LICENSE
ctrlv-0.0.1.dist-info/METADATA
ctrlv-0.0.1.dist-info/WHEEL
ctrlv-0.0.1.dist-info/entry_points.txt
ctrlv-0.0.1.dist-info/top_level.txt
ctrlv-0.0.1.dist-info/RECORD
