Metadata-Version: 2.1
Name: ctrlv
Version: 0.0.1
Summary: Code snippet store
Home-page: UNKNOWN
Author: Bitto Bennichan
Author-email: bittobennichan@protonmail.com
License: MIT
Platform: any
Classifier: Environment :: Web Environment
Classifier: Intended Audience :: Developers
Classifier: License :: OSI Approved :: MIT License
Classifier: Operating System :: OS Independent
Classifier: Programming Language :: Python
Classifier: Programming Language :: Python :: 3
Classifier: Programming Language :: Python :: 3.6
Classifier: Programming Language :: Python :: 3.7
Classifier: Topic :: Internet :: WWW/HTTP :: Dynamic Content
Requires-Python: >=3.6
Requires-Dist: beautifulsoup4
Requires-Dist: Flask-Login
Requires-Dist: Flask-MDE (>=1.1.2)
Requires-Dist: Flask-SQLAlchemy
Requires-Dist: Flask-WTF
Requires-Dist: html5lib
Requires-Dist: Markdown
Requires-Dist: waitress
Requires-Dist: bleach
